sekm_pump/__init__.py
sekm_pump/api_client.py
sekm_pump/configuration.py
sekm_pump/rest.py
sekm_pump/api/__init__.py
sekm_pump/api/public_api.py
sekm_pump/models/__init__.py
sekm_pump/models/three_state_type.py
test/__init__.py
test/test_public_api.py
test/test_three_state_type.py
sekm_pump-1.0.0.9.dist-info/LICENSE
sekm_pump-1.0.0.9.dist-info/METADATA
sekm_pump-1.0.0.9.dist-info/WHEEL
sekm_pump-1.0.0.9.dist-info/top_level.txt
sekm_pump-1.0.0.9.dist-info/RECORD
