Metadata-Version: 2.1
Name: sekm-pump
Version: 1.0.0.9
Summary: SYSNET SEKM Pump REST API client
Home-page: 
Author-email: Radim Jaeger <rjaeger@sysnet.cz>
License: Apache License
Project-URL: Homepage, https://github.com/SYSNET-CZ/swagger/tree/main/clients/sekm_pump
Keywords: Swagger,SEKM analytical data API
Classifier: Programming Language :: Python :: 3
Classifier: Development Status :: 4 - Beta
Classifier: Framework :: Flask
Classifier: Intended Audience :: Developers
Classifier: License :: OSI Approved :: Apache Software License
Classifier: Natural Language :: Czech
Classifier: Operating System :: OS Independent
Classifier: Programming Language :: Python :: 3
Classifier: Topic :: Software Development :: Libraries :: Python Modules
Requires-Python: >=3.9
License-File: LICENSE
Requires-Dist: urllib3 (>=1.15)
Requires-Dist: six (>=1.10)
Requires-Dist: certifi
Requires-Dist: python-dateutil
